heatmouse/__init__.py
heatmouse/__main__.py
heatmouse/_version.py
heatmouse/activeicon.py
heatmouse/activewindow.py
heatmouse/database.py
heatmouse/heatmouse.ui
heatmouse/heatmouse_main.py
heatmouse/listener.py
heatmouse/listitemdelegate.py
heatmouse/mainwindow.py
heatmouse/threadworker.py
heatmouse/images/Gemini_Generated_Image_2fqe2e2fqe2e2fqe-Photoroom.png
heatmouse/images/heatmouse.ico
heatmouse/images/heatmouse.png
heatmouse/images/heatmouse_title_big.png
heatmouse/images/noicon.png
heatmouse/images/play.png
heatmouse/images/stop.png
heatmouse/resources/PublicPixel.ttf
heatmouse-1.0.2.dist-info/licenses/LICENSE
heatmouse-1.0.2.dist-info/METADATA
heatmouse-1.0.2.dist-info/WHEEL
heatmouse-1.0.2.dist-info/top_level.txt
heatmouse-1.0.2.dist-info/RECORD
