Metadata-Version: 2.4
Name: heatmouse
Version: 1.0.2
Summary: Heat Mouse
Author-email: Benjamin Katz <benjaminkatz04@gmail.com>
License: MIT License
Project-URL: Homepage, https://github.com/benjamink04/heat-mouse
Project-URL: Repository, https://github.com/benjamink04/heat-mouse
Project-URL: Issues, https://github.com/benjamink04/heat-mouse/issues
Project-URL: Documentation, https://github.com/benjamink04/heat-mouse/wiki
Classifier: Development Status :: 4 - Beta
Classifier: Environment :: Console
Classifier: Intended Audience :: Science/Research
Classifier: Intended Audience :: Developers
Classifier: Operating System :: Microsoft :: Windows
Classifier: Programming Language :: Python :: 3
Classifier: Programming Language :: Python :: 3.7
Classifier: Programming Language :: Python :: 3.8
Classifier: Programming Language :: Python :: 3.11
Requires-Python: >=3.7
License-File: LICENSE
Requires-Dist: pynput>=1.8.1
Requires-Dist: PyQt5
Requires-Dist: matplotlib
Requires-Dist: pywin32
Requires-Dist: pillow
Requires-Dist: psutil
Requires-Dist: pandas
Requires-Dist: numpy
Requires-Dist: astropy
Dynamic: license-file
